jfrog_ml/__init__.py
jfrog_ml/_artifactory_api.py
jfrog_ml/_environment.py
jfrog_ml/_log_config.py
jfrog_ml/_storage_utils.py
jfrog_ml/_utils.py
jfrog_ml/artifactory.py
jfrog_ml/http/__init__.py
jfrog_ml/http/http_client.py
jfrog_ml/model_info.py
jfrog_ml/storage.py
jfrog_ml-1.0.3.dist-info/WHEEL
jfrog_ml-1.0.3.dist-info/METADATA
jfrog_ml-1.0.3.dist-info/licenses/LICENSE
jfrog_ml-1.0.3.dist-info/RECORD
