Metadata-Version: 2.1
Name: jfrog_ml
Version: 1.0.3
Summary: JFrog ML package
Author-email: JFrog <Shayb@jfrog.com>
Requires-Python: >=3.9
Classifier: Operating System :: OS Independent
Classifier: Programming Language :: Python :: 3
Project-URL: Homepage, https://github.com/jfrog/frogml
Project-URL: Issues, https://github.com/jfrog/frogml/issues
